cthread/__init__.py
cthread/cthread.py
cthread-1.2.1.dist-info/LICENSE.rst
cthread-1.2.1.dist-info/METADATA
cthread-1.2.1.dist-info/WHEEL
cthread-1.2.1.dist-info/top_level.txt
cthread-1.2.1.dist-info/RECORD
